videosdk/plugins/simli/__init__.py
videosdk/plugins/simli/simli.py
videosdk/plugins/simli/version.py
videosdk_plugins_simli-0.0.58.dist-info/METADATA
videosdk_plugins_simli-0.0.58.dist-info/WHEEL
videosdk_plugins_simli-0.0.58.dist-info/RECORD
