Metadata-Version: 2.4
Name: videosdk-plugins-simli
Version: 0.0.58
Summary: VideoSDK Agent Framework plugin for Simli Virtual Avatar
Author: videosdk
Keywords: ai,audio,simli,video,videosdk
Classifier: Development Status :: 4 - Beta
Classifier: Intended Audience :: Developers
Classifier: Topic :: Communications :: Conferencing
Classifier: Topic :: Multimedia :: Sound/Audio
Classifier: Topic :: Multimedia :: Video
Classifier: Topic :: Scientific/Engineering :: Artificial Intelligence
Requires-Python: >=3.12
Requires-Dist: simli-ai>=1.0.3
Requires-Dist: videosdk-agents>=0.0.58
